{"cameraMode":{"drawMode":0,"name":"Shaded","section":"Shading Mode"},"sceneLighting":true,"audioPlay":false,"sceneViewState":{"m_AlwaysRefresh":false,"showFog":true,"showSkybox":true,"showFlares":true,"showImageEffects":true,"showParticleSystems":true,"showVisualEffectGraphs":true,"m_FxEnabled":true},"in2DMode":false,"pivot":{"x":285.33453369140627,"y":-6.215279579162598,"z":30.24656105041504},"rotation":{"x":0.1098916232585907,"y":0.837708055973053,"z":-0.18620295822620393,"w":0.5026219487190247},"size":27.62883186340332,"orthographic":false}